docs/conf.py
esapp/__init__.py
esapp/gobject.py
esapp/grid.py
esapp/indexable.py
esapp/workbench.py
esapp/apps/__init__.py
esapp/apps/dynamics.py
esapp/apps/gic.py
esapp/apps/modes.py
esapp/apps/network.py
esapp/apps/static.py
esapp/dev/generate_components.py
esapp/saw/__init__.py
esapp/saw/_exceptions.py
esapp/saw/_helpers.py
esapp/saw/atc.py
esapp/saw/base.py
esapp/saw/case_actions.py
esapp/saw/contingency.py
esapp/saw/fault.py
esapp/saw/general.py
esapp/saw/gic.py
esapp/saw/matrices.py
esapp/saw/modify.py
esapp/saw/oneline.py
esapp/saw/opf.py
esapp/saw/powerflow.py
esapp/saw/pv.py
esapp/saw/qv.py
esapp/saw/regions.py
esapp/saw/saw.py
esapp/saw/scheduled.py
esapp/saw/sensitivity.py
esapp/saw/timestep.py
esapp/saw/topology.py
esapp/saw/transient.py
esapp/saw/weather.py
esapp/utils/__init__.py
esapp/utils/b3d.py
esapp/utils/decorators.py
esapp/utils/exceptions.py
esapp/utils/map.py
esapp/utils/mathtools.py
esapp/utils/mesh.py
esapp/utils/misc.py
esapp/utils/plotwavelet.py
esapp/utils/shapes/Texas/Shape.cpg
esapp/utils/shapes/Texas/Shape.dbf
esapp/utils/shapes/Texas/Shape.prj
esapp/utils/shapes/Texas/Shape.shp
esapp/utils/shapes/Texas/Shape.shx
esapp/utils/shapes/US/Shape.cpg
esapp/utils/shapes/US/Shape.dbf
esapp/utils/shapes/US/Shape.prj
esapp/utils/shapes/US/Shape.shp
esapp/utils/shapes/US/Shape.shp.ea.iso.xml
esapp/utils/shapes/US/Shape.shx
esapp/utils/shapes/US/Shape.xml
esapp-0.1.1.dist-info/licenses/LICENSE
examples/example_get_subdata.py
tests/config_test.example.py
tests/conftest.py
tests/test_apps_network_gic.py
tests/test_exceptions.py
tests/test_grid_components.py
tests/test_indexable_data_access.py
tests/test_integration_analysis.py
tests/test_integration_contingency.py
tests/test_integration_powerflow.py
tests/test_integration_saw_powerworld.py
tests/test_integration_workbench.py
tests/test_saw_core_methods.py
tests/test_workbench.py
esapp-0.1.1.dist-info/METADATA
esapp-0.1.1.dist-info/WHEEL
esapp-0.1.1.dist-info/top_level.txt
esapp-0.1.1.dist-info/RECORD
