Metadata-Version: 2.4
Name: esapp
Version: 0.1.1
Summary: ESA++ is an open-source power-grid toolkit.
Author-email: Adam Birchfield <abirchfield@tamu.edu>, Luke Lowery <wyattluke.lowery@tamu.edu>
License: Apache License 2.0
Project-URL: Homepage, https://github.com/lukelowry/ESApp
Keywords: Python,PowerWorld,PowerWorld Simulator,Simulator,PowerWorld Simulation Automation Server,SimAuto,Automation,Power Systems,Electric Power,Power,Easy SimAuto,ESA,ESAplus,Smart Grid
Classifier: Programming Language :: Python :: 3 :: Only
Classifier: Programming Language :: Python :: 3.7
Classifier: Programming Language :: Python :: 3.8
Classifier: Programming Language :: Python :: 3.9
Classifier: Programming Language :: Python :: 3.10
Classifier: License :: OSI Approved :: Apache Software License
Classifier: Operating System :: Microsoft :: Windows
Classifier: Development Status :: 5 - Production/Stable
Classifier: Environment :: Win32 (MS Windows)
Classifier: Intended Audience :: Developers
Classifier: Intended Audience :: Education
Classifier: Intended Audience :: Science/Research
Classifier: Natural Language :: English
Classifier: Topic :: Education
Classifier: Topic :: Scientific/Engineering
Classifier: Topic :: Software Development
Requires-Python: >=3.7
License-File: LICENSE
Requires-Dist: pandas
Requires-Dist: numpy<2.0
Requires-Dist: scipy
Requires-Dist: pywin32; sys_platform == "win32"
Requires-Dist: geopandas
Requires-Dist: matplotlib
Provides-Extra: test
Requires-Dist: pytest>=7.0; extra == "test"
Requires-Dist: pytest-cov>=4.0; extra == "test"
Requires-Dist: pytest-xdist>=3.0; extra == "test"
Requires-Dist: pytest-timeout>=2.1; extra == "test"
Requires-Dist: pytest-mock>=3.10; extra == "test"
Requires-Dist: pytest-order>=1.2; extra == "test"
Provides-Extra: dev
Requires-Dist: matplotlib; extra == "dev"
Requires-Dist: pytest>=7.0; extra == "dev"
Requires-Dist: pytest-cov>=4.0; extra == "dev"
Requires-Dist: pytest-order>=1.2; extra == "dev"
Provides-Extra: docs
Requires-Dist: sphinx; extra == "docs"
Requires-Dist: sphinx-rtd-theme; extra == "docs"
Requires-Dist: sphinx-copybutton; extra == "docs"
Requires-Dist: nbsphinx; extra == "docs"
Requires-Dist: ipykernel; extra == "docs"
Requires-Dist: matplotlib; extra == "docs"
Dynamic: license-file
